django_fsm_ex/__init__.py
django_fsm_ex/decorators.py
django_fsm_ex/errors.py
django_fsm_ex/fields.py
django_fsm_ex/management/__init__.py
django_fsm_ex/management/commands/__init__.py
django_fsm_ex/management/commands/graph_transitions.py
django_fsm_ex/models.py
django_fsm_ex/signals.py
django_fsm_ex/tests/__init__.py
django_fsm_ex/tests/test_basic_transitions.py
django_fsm_ex/tests/test_conditions.py
django_fsm_ex/tests/test_inheritance.py
django_fsm_ex/tests/test_integer_field.py
django_fsm_ex/tests/test_key_field.py
django_fsm_ex/tests/test_protected_field.py
django_fsm_ex/transition.py
django_fsm_ex/types.py
django_fsm_ex-3.1.0.dist-info/LICENSE
django_fsm_ex-3.1.0.dist-info/WHEEL
django_fsm_ex-3.1.0.dist-info/METADATA
django_fsm_ex-3.1.0.dist-info/RECORD
