Metadata-Version: 2.1
Name: django-fsm-ex
Version: 3.1.0
Summary: 一个基于 Django 有限状态管理工具库,基于 django-fsm 修改
Home-page: https://github.com/banxi1988/django-fsm
Keywords: Django,transition,FSMField
Author: codetalks
Author-email: banxi1988@gmail.com
Requires-Python: >=3.6,<4.0
Classifier: Programming Language :: Python :: 3
Classifier: Programming Language :: Python :: 3.6
Classifier: Programming Language :: Python :: 3.7
Provides-Extra: commands
Requires-Dist: django (>=2.2,<3.0)
Requires-Dist: graphviz (>=0.10,<0.11); extra == "commands"
Project-URL: Repository, https://github.com/banxi1988/django-fsm
